django_es-0.0.5.dist-info/WHEEL
django_es-0.0.5.dist-info/metadata.json
django_es-0.0.5.dist-info/DESCRIPTION.rst
django_es-0.0.5.dist-info/top_level.txt
django_es-0.0.5.dist-info/dependency_links.txt
django_es-0.0.5.dist-info/RECORD
django_es-0.0.5.dist-info/METADATA
django_es/fields.py
django_es/utils.py
django_es/decorators.py
django_es/__init__.py
django_es/apps.py
django_es/indices.py
django_es/mappings.py
django_es/signals/pre_saved.py
django_es/signals/has_changed.py
django_es/signals/__init__.py
django_es/signals/base.py
