Metadata-Version: 2.0
Name: django-es
Version: 0.0.5
Summary: A Django elasticsearch wrapper for model and helper using elasticsearch-dsl-py high level library.
Home-page: https://github.com/GuillaumeCisco/django-es
Author: Guillaume Cisco
Author-email: guillaumecisco@gmail.com
License: BSD-3
Keywords: elasticsearch haystack django bungiesearch django_es
Platform: UNKNOWN
Classifier: Development Status :: 5 - Production/Stable
Classifier: Intended Audience :: Developers
Classifier: License :: OSI Approved :: BSD License
Classifier: Operating System :: OS Independent
Classifier: Programming Language :: Python :: 2
Classifier: Framework :: Django
Requires-Dist: django (>=1.8)
Requires-Dist: elasticsearch-dsl (>=5.3.0)
Requires-Dist: elasticsearch (>=5.4.0)
Requires-Dist: python-dateutil
Requires-Dist: six
